[
  {
    "field_name": "Naslov",
    "prop_name": "title",
    "in_main_table": true,
    "in_details": true,
    "editable": true,
    "disabled": false,
    "required": true,
    "description": "",
    "ui_prop": "xyz",
    "sortable": true,
    "input_type": "input"
  },
  {
      "field_name": "Thumb slika",
      "prop_name": "thumb_image",
      "validate": {
          "imageUpload": null
      },
      "in_main_table": true,
      "in_details": true,
      "editable": true,
      "disabled": false,
      "required": true,
      "description": "",
      "ui_prop": {
          "fileUpload": {
              "fillFromApi": "admin/news-b2c/news/basic-data/options/upload",
              "allow_format": [],
              "allow_size": "",
              "image": {
                  "convert_use": null,
                  "width": "1920",
                  "height": "1080"
              }
          }
      },
      "sortable": true,
      "input_type": "image_button"
  },
  {
    "field_name": "Kratak opis",
    "prop_name": "short_description",
    "in_main_table": true,
    "in_details": true,
    "editable": true,
    "disabled": false,
    "required": false,
    "description": "",
    "ui_prop": "xyz",
    "sortable": true,
    "input_type": "textarea"
  },
  {
    "field_name": "Opis",
    "prop_name": "description",
    "in_main_table": true,
    "in_details": true,
    "editable": true,
    "disabled": false,
    "required": false,
    "description": "",
    "ui_prop": "xyz",
    "sortable": true,
    "input_type": "html_editor"
  },
  {
    "field_name": "Tagovi",
    "prop_name": "tag",
    "in_main_table": true,
    "in_details": true,
    "editable": true,
    "disabled": false,
    "required": false,
    "description": "",
    "ui_prop": "xyz",
    "sortable": true,
    "input_type": "autocomplete_tags_filled",
    "fillFromApi": "admin/news-b2c/news/basic-data/ddl",
    "usePropName": true,
    "options": []
  },
  {
    "field_name": "Datum objave",
    "prop_name": "publish_at",
    "in_main_table": true,
    "in_details": true,
    "editable": true,
    "disabled": false,
    "required": false,
    "description": "",
    "ui_prop": "xyz",
    "sortable": true,
    "input_type": "date_time"
  },
  {
    "field_name": "Autor",
    "prop_name": "author",
    "in_main_table": true,
    "in_details": true,
    "editable": true,
    "disabled": false,
    "required": false,
    "description": "",
    "ui_prop": "xyz",
    "sortable": true,
    "input_type": "input"
  },
  {
    "field_name": "Pozicija",
    "prop_name": "order",
    "in_main_table": true,
    "in_details": true,
    "editable": true,
    "disabled": false,
    "required": false,
    "description": "",
    "ui_prop": "xyz",
    "sortable": true,
    "input_type": "number"
  },
  {
    "field_name": "Status",
    "prop_name": "status",
    "in_main_table": true,
    "in_details": true,
    "editable": true,
    "disabled": false,
    "required": true,
    "description": "",
    "ui_prop": "xyz",
    "sortable": true,
    "input_type": "select",
    "fillFromApi": "admin/news-b2c/news/basic-data/ddl",
    "usePropName": true,
    "options": []
  }
]
